README.md
easy_to_hard_data.py
easy_to_hard_plot.py
setup.py
easy_to_hard_data.egg-info/PKG-INFO
easy_to_hard_data.egg-info/SOURCES.txt
easy_to_hard_data.egg-info/dependency_links.txt
easy_to_hard_data.egg-info/requires.txt
easy_to_hard_data.egg-info/top_level.txt