Metadata-Version: 2.1
Name: easy-to-hard-data
Version: 1.0.0
Summary: Easy to Hard Data
Home-page: https://aks2203.github.io/easy-to-hard-data
Author: Avi Schwarzschild
License: MIT
Keywords: pytorch,generalization,machine learning
Platform: UNKNOWN
Requires-Python: >=3.7
